Workbook

Sheet Data Entry
A1: NSE SHARIA SCREENER — DATA COLLECTION (NSE 20)
A2: Blue = your input | Gray = auto-calculated | Red = auto-fail (haram sector or ratio breach)
A3: Company | B3: Ticker | C3: Sector | D3: Total Assets (Sh.m) | E3: Total Debt (interest-bearing) | F3: Revenue (Sh.m) | G3: Interest/Finance Income (Sh.m) | H3: Cash + Trade Receivables (Sh.m) | I3: Debt/ Assets | J3: Interest/ Revenue | K3: Liq./ Assets | L3: Layer 1 Pass? | M3: Layer 2 Pass? | N3: Score 0–100 | O3: Rating
A4: Safaricom | B4: SCOM | C4: Telecom | D4: 641164.3 | E4: 108146.8 | F4: 349447.2 | G4: 5459.6 | H4: 70987.2 | I4: =IFERROR(E4/D4,"") -> 0.16867252 | J4: =IFERROR(G4/F4,"") -> 0.015623533 | K4: =IFERROR(H4/D4,"") -> 0.11071608 | L4: YES | M4: =IFERROR(IF(AND(I4<0.33,J4<0.05,K4<0.33),"YES","NO"),"") -> YES | N4: =IFERROR(40+IF(I4<0.33,20,IF(I4<0.5,10,0))+IF(J4<0.05,20,IF(J4<0.1,10,0))+IF(K4<0.33,20,IF(K4<0.5,10,0)),0) -> 100 | O4: =IFERROR(IF(N4>=80,"A",IF(N4>=60,"B",IF(N4>=40,"C","D"))),"") -> A
A5: Bamburi Cement | B5: BAMB | C5: Manufacturing | D5: 33006 | E5: 0 | F5: 41381 | G5: 310 | H5: 7121 | I5: =IFERROR(E5/D5,"") -> 0 | J5: =IFERROR(G5/F5,"") -> 0.0074913608 | K5: =IFERROR(H5/D5,"") -> 0.21574865 | L5: YES | M5: =IFERROR(IF(AND(I5<0.33,J5<0.05,K5<0.33),"YES","NO"),"") -> YES | N5: =IFERROR(40+IF(I5<0.33,20,IF(I5<0.5,10,0))+IF(J5<0.05,20,IF(J5<0.1,10,0))+IF(K5<0.33,20,IF(K5<0.5,10,0)),0) -> 100 | O5: =IFERROR(IF(N5>=80,"A",IF(N5>=60,"B",IF(N5>=40,"C","D"))),"") -> A
A6: Kenya Airways | B6: KQ | C6: Aviation | D6: 179104 | E6: 148085 | F6: 188495 | G6: 69 | H6: 26142 | I6: =IFERROR(E6/D6,"") -> 0.82681012 | J6: =IFERROR(G6/F6,"") -> 0.00036605746 | K6: =IFERROR(H6/D6,"") -> 0.14595989 | L6: YES | M6: =IFERROR(IF(AND(I6<0.33,J6<0.05,K6<0.33),"YES","NO"),"") -> NO | N6: =IFERROR(40+IF(I6<0.33,20,IF(I6<0.5,10,0))+IF(J6<0.05,20,IF(J6<0.1,10,0))+IF(K6<0.33,20,IF(K6<0.5,10,0)),0) -> 80 | O6: =IFERROR(IF(N6>=80,"A",IF(N6>=60,"B",IF(N6>=40,"C","D"))),"") -> A
A7: Nation Media | B7: NMG | C7: Media | D7: 10700.5 | E7: 0 | F7: 6229.6 | G7: 270.6 | H7: 4568.2 | I7: =IFERROR(E7/D7,"") -> 0 | J7: =IFERROR(G7/F7,"") -> 0.043437781 | K7: =IFERROR(H7/D7,"") -> 0.42691463 | L7: YES | M7: =IFERROR(IF(AND(I7<0.33,J7<0.05,K7<0.33),"YES","NO"),"") -> NO | N7: =IFERROR(40+IF(I7<0.33,20,IF(I7<0.5,10,0))+IF(J7<0.05,20,IF(J7<0.1,10,0))+IF(K7<0.33,20,IF(K7<0.5,10,0)),0) -> 90 | O7: =IFERROR(IF(N7>=80,"A",IF(N7>=60,"B",IF(N7>=40,"C","D"))),"") -> A
A8: Centum Invest. | B8: CTUM | C8: Investment | D8: 76171.9 | E8: 1614.4 | F8: 6332.4 | G8: 607.4 | H8: 9659.5 | I8: =IFERROR(E8/D8,"") -> 0.021194167 | J8: =IFERROR(G8/F8,"") -> 0.095919399 | K8: =IFERROR(H8/D8,"") -> 0.12681186 | L8: YES | M8: =IFERROR(IF(AND(I8<0.33,J8<0.05,K8<0.33),"YES","NO"),"") -> NO | N8: =IFERROR(40+IF(I8<0.33,20,IF(I8<0.5,10,0))+IF(J8<0.05,20,IF(J8<0.1,10,0))+IF(K8<0.33,20,IF(K8<0.5,10,0)),0) -> 90 | O8: =IFERROR(IF(N8>=80,"A",IF(N8>=60,"B",IF(N8>=40,"C","D"))),"") -> A
A9: Jubilee Hold. | B9: JUB | C9: Insurance | D9: 251082.9 | E9: 0 | F9: 29920.9 | G9: 22572.2 | H9: 11144.5 | I9: =IFERROR(E9/D9,"") -> 0 | J9: =IFERROR(G9/F9,"") -> 0.75439576 | K9: =IFERROR(H9/D9,"") -> 0.044385739 | L9: YES | M9: =IFERROR(IF(AND(I9<0.33,J9<0.05,K9<0.33),"YES","NO"),"") -> NO | N9: =IFERROR(40+IF(I9<0.33,20,IF(I9<0.5,10,0))+IF(J9<0.05,20,IF(J9<0.1,10,0))+IF(K9<0.33,20,IF(K9<0.5,10,0)),0) -> 80 | O9: =IFERROR(IF(N9>=80,"A",IF(N9>=60,"B",IF(N9>=40,"C","D"))),"") -> A
A10: Britam Hold. | B10: BRIT | C10: Insurance | D10: 208531.8 | E10: 1100.6 | F10: 37556.7 | G10: 19408.4 | H10: 9224.8 | I10: =IFERROR(E10/D10,"") -> 0.0052778521 | J10: =IFERROR(G10/F10,"") -> 0.51677597 | K10: =IFERROR(H10/D10,"") -> 0.044236898 | L10: YES | M10: =IFERROR(IF(AND(I10<0.33,J10<0.05,K10<0.33),"YES","NO"),"") -> NO | N10: =IFERROR(40+IF(I10<0.33,20,IF(I10<0.5,10,0))+IF(J10<0.05,20,IF(J10<0.1,10,0))+IF(K10<0.33,20,IF(K10<0.5,10,0)),0) -> 80 | O10: =IFERROR(IF(N10>=80,"A",IF(N10>=60,"B",IF(N10>=40,"C","D"))),"") -> A
A11: CIC Insurance | B11: CIC | C11: Insurance | D11: 61937.7 | E11: 5271.4 | F11: 26348.8 | G11: 6046.4 | H11: 1751.8 | I11: =IFERROR(E11/D11,"") -> 0.085108101 | J11: =IFERROR(G11/F11,"") -> 0.22947535 | K11: =IFERROR(H11/D11,"") -> 0.028283259 | L11: YES | M11: =IFERROR(IF(AND(I11<0.33,J11<0.05,K11<0.33),"YES","NO"),"") -> NO | N11: =IFERROR(40+IF(I11<0.33,20,IF(I11<0.5,10,0))+IF(J11<0.05,20,IF(J11<0.1,10,0))+IF(K11<0.33,20,IF(K11<0.5,10,0)),0) -> 80 | O11: =IFERROR(IF(N11>=80,"A",IF(N11>=60,"B",IF(N11>=40,"C","D"))),"") -> A
A12: Kenya Power | B12: KPLC | C12: Utility | D12: 389039 | E12: 87640 | F12: 219285 | G12: 625 | H12: 98370 | I12: =IFERROR(E12/D12,"") -> 0.22527304 | J12: =IFERROR(G12/F12,"") -> 0.0028501722 | K12: =IFERROR(H12/D12,"") -> 0.25285383 | L12: YES | M12: =IFERROR(IF(AND(I12<0.33,J12<0.05,K12<0.33),"YES","NO"),"") -> YES | N12: =IFERROR(40+IF(I12<0.33,20,IF(I12<0.5,10,0))+IF(J12<0.05,20,IF(J12<0.1,10,0))+IF(K12<0.33,20,IF(K12<0.5,10,0)),0) -> 100 | O12: =IFERROR(IF(N12>=80,"A",IF(N12>=60,"B",IF(N12>=40,"C","D"))),"") -> A
A13: Equity Group | B13: EQTY | C13: Banking | D13: — | E13: — | F13: — | G13: — | H13: — | I13: — | J13: — | K13: — | L13: NO | M13: NO | N13: 0 | O13: D
A14: KCB Group | B14: KCB | C14: Banking | D14: — | E14: — | F14: — | G14: — | H14: — | I14: — | J14: — | K14: — | L14: NO | M14: NO | N14: 0 | O14: D
A15: Cooperative Bk | B15: COOP | C15: Banking | D15: — | E15: — | F15: — | G15: — | H15: — | I15: — | J15: — | K15: — | L15: NO | M15: NO | N15: 0 | O15: D
A16: Std Chartered | B16: SCBK | C16: Banking | D16: — | E16: — | F16: — | G16: — | H16: — | I16: — | J16: — | K16: — | L16: NO | M16: NO | N16: 0 | O16: D
A17: ABSA Bank | B17: ABSA | C17: Banking | D17: — | E17: — | F17: — | G17: — | H17: — | I17: — | J17: — | K17: — | L17: NO | M17: NO | N17: 0 | O17: D
A18: Diamond Trust | B18: DTK | C18: Banking | D18: — | E18: — | F18: — | G18: — | H18: — | I18: — | J18: — | K18: — | L18: NO | M18: NO | N18: 0 | O18: D
A19: NCBA Group | B19: NCBA | C19: Banking | D19: — | E19: — | F19: — | G19: — | H19: — | I19: — | J19: — | K19: — | L19: NO | M19: NO | N19: 0 | O19: D
A20: I&M Group | B20: IMH | C20: Banking | D20: — | E20: — | F20: — | G20: — | H20: — | I20: — | J20: — | K20: — | L20: NO | M20: NO | N20: 0 | O20: D
A21: Stanbic Hold. | B21: CFC | C21: Banking | D21: — | E21: — | F21: — | G21: — | H21: — | I21: — | J21: — | K21: — | L21: NO | M21: NO | N21: 0 | O21: D
A22: EA Breweries | B22: EABL | C22: Alcohol | D22: — | E22: — | F22: — | G22: — | H22: — | I22: — | J22: — | K22: — | L22: NO | M22: NO | N22: 0 | O22: D
A23: BAT Kenya | B23: BAT | C23: Tobacco | D23: — | E23: — | F23: — | G23: — | H23: — | I23: — | J23: — | K23: — | L23: NO | M23: NO | N23: 0 | O23: D

Sheet Results Summary
A1: SHARIA SCREEN RESULTS — NSE 20
A2: Company | B2: Sector | C2: Layer 1 | D2: Layer 2 | E2: Score | F2: Rating
A3: Safaricom | B3: Telecom | C3: ='Data Entry'!L4 -> YES | D3: ='Data Entry'!M4 -> YES | E3: ='Data Entry'!N4 -> 100 | F3: ='Data Entry'!O4 -> A
A4: Bamburi Cement | B4: Manufacturing | C4: ='Data Entry'!L5 -> YES | D4: ='Data Entry'!M5 -> YES | E4: ='Data Entry'!N5 -> 100 | F4: ='Data Entry'!O5 -> A
A5: Kenya Airways | B5: Aviation | C5: ='Data Entry'!L6 -> YES | D5: ='Data Entry'!M6 -> NO | E5: ='Data Entry'!N6 -> 80 | F5: ='Data Entry'!O6 -> A
A6: Nation Media | B6: Media | C6: ='Data Entry'!L7 -> YES | D6: ='Data Entry'!M7 -> NO | E6: ='Data Entry'!N7 -> 90 | F6: ='Data Entry'!O7 -> A
A7: Centum Invest. | B7: Investment | C7: ='Data Entry'!L8 -> YES | D7: ='Data Entry'!M8 -> NO | E7: ='Data Entry'!N8 -> 90 | F7: ='Data Entry'!O8 -> A
A8: Jubilee Hold. | B8: Insurance | C8: ='Data Entry'!L9 -> YES | D8: ='Data Entry'!M9 -> NO | E8: ='Data Entry'!N9 -> 80 | F8: ='Data Entry'!O9 -> A
A9: Britam Hold. | B9: Insurance | C9: ='Data Entry'!L10 -> YES | D9: ='Data Entry'!M10 -> NO | E9: ='Data Entry'!N10 -> 80 | F9: ='Data Entry'!O10 -> A
A10: CIC Insurance | B10: Insurance | C10: ='Data Entry'!L11 -> YES | D10: ='Data Entry'!M11 -> NO | E10: ='Data Entry'!N11 -> 80 | F10: ='Data Entry'!O11 -> A
A11: Kenya Power | B11: Utility | C11: ='Data Entry'!L12 -> YES | D11: ='Data Entry'!M12 -> YES | E11: ='Data Entry'!N12 -> 100 | F11: ='Data Entry'!O12 -> A
A12: Equity Group | B12: Banking | C12: ='Data Entry'!L13 -> NO | D12: ='Data Entry'!M13 -> NO | E12: ='Data Entry'!N13 -> 0 | F12: ='Data Entry'!O13 -> D
A13: KCB Group | B13: Banking | C13: ='Data Entry'!L14 -> NO | D13: ='Data Entry'!M14 -> NO | E13: ='Data Entry'!N14 -> 0 | F13: ='Data Entry'!O14 -> D
A14: Cooperative Bk | B14: Banking | C14: ='Data Entry'!L15 -> NO | D14: ='Data Entry'!M15 -> NO | E14: ='Data Entry'!N15 -> 0 | F14: ='Data Entry'!O15 -> D
... A22: BAT Kenya | B22: Tobacco | C22: ='Data Entry'!L23 -> NO | D22: ='Data Entry'!M23 -> NO | E22: ='Data Entry'!N23 -> 0 | F22: ='Data Entry'!O23 -> D

Sheet Data Notes
A1: DATA SOURCES & NOTES
A2: Company | B2: Notes on data source and figures used
A3: Safaricom | B3: FY2024 consolidated. Assets 641,164M. Debt = LT 63,093 + ST 45,054. Revenue 349,447M. Finance income 5,460M. Cash 22,868 + Receivables 48,119.
A4: Bamburi Cement | B4: FY2024 consolidated. Assets 33,006M. No borrowings (nil 2024). Revenue 41,381M (from revenue summary). Finance income 310M. Cash 5,249 + Receivables 1,872.
A5: Kenya Airways | B5: FY2024. Assets 179,104M. Debt = LT 126,300 + ST 21,785. Revenue 188,495M. Interest income 69M. Cash 5,781 + Receivables 20,361.
A6: Nation Media | B6: FY2024 consolidated. Assets 10,700.5M. No borrowings. Revenue 6,229.6M. Finance income 270.6M. Cash 1,342 + Receivables 3,226.
A7: Centum Invest. | B7: FY March 2024. Figures in KShs'000 converted to millions. Assets 76,171.9M. Debt 1,614.4M. Revenue = trading + real estate 6,332.4M. Finance income 607.4M. Cash + receivables 9,659.5M.
A8: Jubilee Hold. | B8: FY2025 (Dec 2025). Figures in KShs'000 converted to millions. Assets 251,082.9M. No borrowings. Revenue = insurance revenue 29,920.9M. Interest revenue 22,572.2M — NOTE: very high ratio flags this company. Cash + receivables 11,144.5M.
A9: Britam Hold. | B9: FY2024. Assets 208,531.8M. Debt 1,100.6M. Revenue = insurance revenue 37,556.7M. Interest income 19,408.4M — NOTE: ratio will flag. Cash 7,079.3 + Receivables 2,145.5.
A10: CIC Insurance | B10: FY2024. Assets 61,937.7M. Borrowings 5,271.4M. Revenue = insurance revenue 26,348.8M. Interest revenue 6,046.4M — ratio will flag. Cash 823.3 + Receivables 928.5.
A11: Kenya Power | B11: FY2025 (June 2025). Assets 389,039M. Debt = loan book 87,640M (per management commentary). Revenue 219,285M. Interest income 625M. Cash 7,685 + current assets 90,685.
A13: KEY INSIGHT | B13: Insurance companies (Jubilee, Britam, CIC) will fail Layer 2 on interest income ratio — their core business model earns interest on investment portfolios, which is riba. This is expected and is a real finding for your screener.
A14: KEY INSIGHT | B14: Kenya Airways has very high debt/assets (82.7%) — will fail Layer 2.
A15: KEY INSIGHT | B15: Kenya Power has high liquidity/assets ratio (~25%) but passes. Debt/assets at 22.5% passes.
